difflib_rs-0.1.3.dist-info/METADATA
difflib_rs-0.1.3.dist-info/WHEEL
difflib_rs-0.1.3.dist-info/licenses/LICENSE
difflib_rs/__init__.py
difflib_rs/__init__.pyi
difflib_rs/difflib_rs.abi3.so
difflib_rs/py.typed
difflib_rs-0.1.3.dist-info/RECORD
