Metadata-Version: 2.4
Name: difflib-rs
Version: 0.1.3
Requires-Dist: pytest>=7.0 ; extra == 'test'
Provides-Extra: test
License-File: LICENSE
Summary: A Rust implementation of Python's difflib.unified_diff with PyO3 bindings
Requires-Python: >=3.10
